fliiq_skillet-0.0.1.dist-info/licenses/LICENSE
skillet_cli/__init__.py
skillet_cli/cli.py
fliiq_skillet-0.0.1.dist-info/METADATA
fliiq_skillet-0.0.1.dist-info/WHEEL
fliiq_skillet-0.0.1.dist-info/entry_points.txt
fliiq_skillet-0.0.1.dist-info/top_level.txt
fliiq_skillet-0.0.1.dist-info/RECORD
