Metadata-Version: 2.4
Name: fliiq-skillet
Version: 0.0.1
Summary: HTTP-native, OpenAPI-first framework for packaging and running reusable skills
Author-email: Fliiq <hello@fliiq.ai>
Classifier: Programming Language :: Python :: 3
Classifier: License :: OSI Approved :: MIT License
Classifier: Operating System :: OS Independent
Requires-Python: >=3.8
License-File: LICENSE
Dynamic: license-file
